{"cameraMode":{"drawMode":0,"name":"Shaded","section":"Shading Mode"},"sceneLighting":false,"audioPlay":false,"sceneViewState":{"m_AlwaysRefresh":false,"showFog":true,"showSkybox":false,"showFlares":true,"showImageEffects":true,"showParticleSystems":true,"showVisualEffectGraphs":true,"m_FxEnabled":true},"in2DMode":false,"pivot":{"x":-1.134256362915039,"y":10.8668851852417,"z":-0.07189464569091797},"rotation":{"x":0.15736143290996552,"y":0.7808984518051148,"z":-0.2175329029560089,"w":0.5640850067138672},"size":15.694498062133789,"orthographic":false}